README.md
setup.cfg
setup.py
pyinverted/__init__.py
pyinverted/helper.py
pyinverted/inverted.py
pyinverted.egg-info/PKG-INFO
pyinverted.egg-info/SOURCES.txt
pyinverted.egg-info/dependency_links.txt
pyinverted.egg-info/top_level.txt