Metadata-Version: 1.0
Name: pyinverted
Version: 0.1
Summary: A inverted files implementation in Python 3.
Home-page: https://github.com/btrevizan/pyinverted
Author: Bernardo Trevizan
Author-email: trevizanbernardo@gmail.com
License: UNKNOWN
Keywords: struct,file,binary,search,inverted,python
Platform: UNKNOWN
